pyUnicodeSteganography/__init__.py
pyUnicodeSteganography/lookalikes.py
pyUnicodeSteganography/snow.py
pyUnicodeSteganography/zerowidth.py
pyUnicodeSteganography/tests/__init__.py
pyUnicodeSteganography/tests/encoding_test.py
pyUnicodeSteganography-0.0.1.dist-info/LICENSE
pyUnicodeSteganography-0.0.1.dist-info/METADATA
pyUnicodeSteganography-0.0.1.dist-info/WHEEL
pyUnicodeSteganography-0.0.1.dist-info/top_level.txt
pyUnicodeSteganography-0.0.1.dist-info/RECORD
