Metadata-Version: 2.1
Name: pyUnicodeSteganography
Version: 0.0.1
Summary: Experimental unicode steganography package
Home-page: https://github.com/grahamwthompson/pyUnicodeSteganography
Author: Graham Thompson
Author-email: grahamwt42@gmail.com
License: UNKNOWN
Project-URL: Bug Tracker, https://github.com/grahamwthompson/pyUnicodeSteganography/issues
Platform: UNKNOWN
Classifier: Programming Language :: Python :: 3
Classifier: License :: OSI Approved :: MIT License
Classifier: Operating System :: OS Independent
Requires-Python: >=3.6
License-File: LICENSE
